stv_ascii_art/__init__.py
stv_ascii_art/main.py
stv_ascii_art/core/__init__.py
stv_ascii_art/core/image_processor.py
stv_ascii_art/core/stv_parse.py
stv_ascii_art/core/video_processor.py
stv_ascii_art/utils/__init__.py
stv_ascii_art/utils/change_text.py
stv_ascii_art/utils/head.py
stv_ascii_art/utils/lic.py
stv_ascii_art/utils/utils.py
stv_ascii_art-0.1.5.dist-info/METADATA
stv_ascii_art-0.1.5.dist-info/WHEEL
stv_ascii_art-0.1.5.dist-info/entry_points.txt
stv_ascii_art-0.1.5.dist-info/top_level.txt
stv_ascii_art-0.1.5.dist-info/RECORD
