Metadata-Version: 2.4
Name: stv_ascii_art
Version: 0.1.5
Summary: Ascii Art 生成工具
Author: 星灿长风v(StarWindv)
Author-email: starwindv.stv@gmail.com
License: MIT
Project-URL: Homepage, https://github.com/StarWindv/scraper_for_images/tree/package
Classifier: License :: OSI Approved :: MIT License
Classifier: Programming Language :: Python :: 3
Classifier: Development Status :: 5 - Production/Stable
Classifier: Intended Audience :: Developers
Classifier: Topic :: Artistic Software
Requires-Python: >=3.7
Requires-Dist: tqdm
Requires-Dist: numpy
Requires-Dist: stv_utils
Requires-Dist: opencv-python
Requires-Dist: pillow
Requires-Dist: torch
